fuzzquery/__init__.py
fuzzquery/fuzzy.py
fuzzquery-2024.5.17.dist-info/LICENSE
fuzzquery-2024.5.17.dist-info/METADATA
fuzzquery-2024.5.17.dist-info/WHEEL
fuzzquery-2024.5.17.dist-info/top_level.txt
fuzzquery-2024.5.17.dist-info/RECORD
