Metadata-Version: 2.1
Name: fuzzquery
Version: 2024.5.17
Summary: A lightwieght package for fuzzy matching.
Author-email: OneMadGypsy <onemadgypsy@gmail.com>
Project-URL: Homepage, https://github.com/OneMadGypsy/fuzzquery
Project-URL: Issues, https://github.com/OneMadGypsy/fuzzquery/issues
Classifier: Programming Language :: Python :: 3
Classifier: License :: OSI Approved :: MIT License
Classifier: Operating System :: OS Independent
Requires-Python: >=3.8
License-File: LICENSE
Requires-Dist: regex >=2024.5.15
